twimage.py
twimage-0.1.2.dist-info/LICENSE
twimage-0.1.2.dist-info/METADATA
twimage-0.1.2.dist-info/WHEEL
twimage-0.1.2.dist-info/entry_points.txt
twimage-0.1.2.dist-info/top_level.txt
twimage-0.1.2.dist-info/RECORD
