Metadata-Version: 2.1
Name: twimage
Version: 0.1.2
Summary: UNKNOWN
Home-page: UNKNOWN
License: MIT
Platform: UNKNOWN
Requires-Dist: Click
